{
  "slug": "2002-2006-lexus-es300-es330-hid-low-beam-headlight-ballast-replacement-instructions",
  "make": "lexus",
  "title": "2002-2006 Lexus ES300 ES330 HID Low Beam Headlight Ballast Replacement Instructions",
  "youtubeId": "RB9PKzQLkIU",
  "description": "Master Technician Viktor G shows the DIY how-to removal and installation procedure.",
  "models": [],
  "years": "",
  "items": [
    {
      "name": "Aftermarket HID ballast",
      "amazonUrl": "https://amzn.to/4qaDS6c",
      "type": "tool"
    },
    {
      "name": "Automotive retainer clip and tool kit",
      "amazonUrl": "https://amzn.to/3W3UUFr",
      "type": "tool"
    },
    {
      "name": "1/4\" impact driver kit",
      "amazonUrl": "https://amzn.to/3IViYaH",
      "type": "tool"
    }
  ],
  "timestamps": [],
  "transcript": ""
}