{
  "slug": "2015-2021-lexus-nx200t-nx300-nx300h-cabin-air-filter-inspection-and-replacement-instructions",
  "make": "lexus",
  "title": "2015-2021 Lexus NX200t NX300 NX300h Cabin Air Filter Inspection And Replacement Instructions",
  "youtubeId": "2O_CqUuUUms",
  "publishedAt": "2023-09-17T17:54:03Z",
  "description": "Master Technician Viktor G shows the DIY how-to removal and installation procedure.",
  "models": [],
  "years": "",
  "items": [
    {
      "name": "Genuine Lexus/Toyota replacement standard cabin filter",
      "amazonUrl": "https://amzn.to/4a0vZIu",
      "type": "tool"
    },
    {
      "name": "Genuine Lexus/Toyota replacement charcoal impregnated cabin filter",
      "amazonUrl": "https://amzn.to/3RnWC2K",
      "type": "part"
    }
  ],
  "timestamps": [],
  "transcript": ""
}