{
  "slug": "2007-2011-toyota-camry-license-plate-light-bulb-replacement-instructions",
  "make": "toyota",
  "title": "2007-2011 Toyota Camry License Plate Light Bulb Replacement Instructions",
  "youtubeId": "MiIEzDcpoRE",
  "publishedAt": "2023-08-09T06:25:08Z",
  "description": "Master Technician Viktor G shows the DIY how-to removal and installation procedure.",
  "models": [],
  "years": "",
  "items": [
    {
      "name": "Ultimate LED upgrade bulb",
      "amazonUrl": "https://amzn.to/3NUzK95",
      "type": "part"
    },
    {
      "name": "Upgraded replacement bulb",
      "amazonUrl": "https://amzn.to/4aOPzYB",
      "type": "part"
    },
    {
      "name": "Standard replacement bulb",
      "amazonUrl": "https://amzn.to/3OfbJZT",
      "type": "tool"
    },
    {
      "name": "Automotive trim and clip removal kit",
      "amazonUrl": "https://amzn.to/3KgKGfg",
      "type": "tool"
    },
    {
      "name": "Replacement aftermarket clips",
      "amazonUrl": "https://amzn.to/4a662rc",
      "type": "tool"
    }
  ],
  "timestamps": [],
  "transcript": ""
}